{

    "__comment": "Made with TheDestruc7i0n's advancements generator: https://advancements.thedestruc7i0n.ca",

    "display": {

        "title": {

            "text": "You'll Fix That... Right?"

        },

        "description": {

            "text": "You just made a creeper explode so you better fix up that hole! Look I even gave you the items for it :D"

        },

        "icon": {

            "item": "minecraft:creeper_head"

        },

        "frame": "task",

        "show_toast": true,

        "announce_to_chat": true,

        "hidden": false

    },

    "criteria": {
        "FixPls": {
            "trigger": "minecraft:entity_hurt_player",
            "conditions": {
                "damage": {
                    "type": {
                        "is_explosion": true
                    }
                }
            }
        },
        "fixlocation": {
            "trigger": "minecraft:location",
            "conditions": {
                "biome": "minecraft:savanna"
            }
        }
    },
    "requirements": [["FixPls"], ["fixlocation"]],
    "parent": "tbdsmp:japannah/japannahexpand"
}